SoiUtils/__init__.py
SoiUtils/general.py
SoiUtils/interfaces.py
SoiUtils/load.py
SoiUtils/output_recorder.py
SoiUtils/parallelization.py
SoiUtils/ronen_api.py
SoiUtils/test_script.py
SoiUtils/video_manipulations.py
SoiUtils/cloud/__init__.py
SoiUtils/cloud/storage.py
SoiUtils/datasets/__init__.py
SoiUtils/datasets/base.py
SoiUtils/datasets/datasets.py
SoiUtils-0.3.1.dist-info/LICENSE
SoiUtils-0.3.1.dist-info/METADATA
SoiUtils-0.3.1.dist-info/WHEEL
SoiUtils-0.3.1.dist-info/top_level.txt
SoiUtils-0.3.1.dist-info/RECORD
