Metadata-Version: 2.1
Name: SoiUtils
Version: 0.3.1
Summary: A Package that includes utility functions
Author: Sharon Komissarov
Author-email: sharon200102@gmail.com
Keywords: python
Classifier: Development Status :: 3 - Alpha
Classifier: Intended Audience :: Education
Classifier: Programming Language :: Python :: 3
License-File: LICENSE
Requires-Dist: numpy
Requires-Dist: opencv-python
Requires-Dist: torch
Requires-Dist: pybboxes
Requires-Dist: fiftyone
Requires-Dist: pycocotools
